sicko/__init__.py
sicko/cli.py
sicko-0.0.2.dist-info/METADATA
sicko-0.0.2.dist-info/WHEEL
sicko-0.0.2.dist-info/entry_points.txt
sicko-0.0.2.dist-info/licenses/LICENSE
sicko-0.0.2.dist-info/RECORD
