Metadata-Version: 2.4
Name: sicko
Version: 0.0.2
Summary: sicko mode python developer experience
Project-URL: Homepage, https://github.com/bharxhav/sicko-py
Project-URL: Repository, https://github.com/bharxhav/sicko-py
Author-email: Bhargav Kantheti <k@bk.bio>
License: IT'S OURS LICENSE, VERSION 1.0
License-File: LICENSE
Requires-Python: >=3.10
